{"cameraMode":{"drawMode":0,"name":"Shaded","section":"Shading Mode"},"sceneLighting":false,"audioPlay":false,"sceneViewState":{"m_AlwaysRefresh":false,"showFog":false,"showSkybox":false,"showFlares":true,"showImageEffects":true,"showParticleSystems":true,"showVisualEffectGraphs":true,"m_FxEnabled":true},"in2DMode":false,"pivot":{"x":148.689208984375,"y":23.776870727539064,"z":168.86029052734376},"rotation":{"x":-0.04494849592447281,"y":-0.9384817481040955,"z":0.3151719570159912,"w":-0.133784681558609},"size":34.46212387084961,"orthographic":false}